app/__init__.py
app/asnc.py
app/borderlayout.py
app/configurationwidgets.py
app/corrector.py
app/gui.py
app/horizontaltab.py
app/imagewidgets.py
app/jobwidgets.py
app/parking_dataset.py
app/statswidgets.py
app/utils.py
app/img/activity_monitor.png
app/img/noimage.png
app/img/pictures-ok.png
app/img/slideshow_report.png
app/img/webcam-control_record.png
parking_app-0.0.6.dist-info/METADATA
parking_app-0.0.6.dist-info/WHEEL
parking_app-0.0.6.dist-info/entry_points.txt
parking_app-0.0.6.dist-info/namespace_packages.txt
parking_app-0.0.6.dist-info/top_level.txt
parking_app-0.0.6.dist-info/RECORD
