Metadata-Version: 2.1
Name: parking-app
Version: 0.0.6
Summary: Parking desktop app
Home-page: https://gitlab.com/optima_iot/parking_desktop_app
Author: Richard Holly
Author-email: rho@optimaideas.com
License: UNKNOWN
Platform: Any
Classifier: Programming Language :: Python :: 3
Classifier: Programming Language :: Python :: 3.6
Classifier: Intended Audience :: Developers
Classifier: Environment :: Console
Requires-Dist: PyQt5
Requires-Dist: imutils
Requires-Dist: pyqtgraph
Requires-Dist: opencv-python
Requires-Dist: requests
Requires-Dist: micropipes-cli (==0.6)
Requires-Dist: qdarkgraystyle
Requires-Dist: Pillow
Requires-Dist: matplotlibgoogle-cloud-storage (==1.26.0)
